barrel_shifter/design/barrel_shifter.v
////////////////////////////////////////
///Cyclic Barrel Shifter
///////////////////////////////////////

// +FHDR-----------------------------------------------------------------------
// FILE NAME : barrel_shifter.v
// AUTHOR : Shanie Winitz
// PURPOSE : Cyclic Barrel Shifter.
// Clock Domains :
// Other :
// -FHDR-----------------------------------------------------------------------


module barrel_shifter #(
    parameter WORD_SIZE = 256,
    parameter NOF_PES = 16,
    parameter NOF_LEVELS = $clog2(NOF_PES) // localparam NOF_LEVELS = $clog2(NOF_PES);
    )(
    input                                   clk,
    input                                   rst,
    input       [WORD_SIZE * NOF_PES -1:0]  in,
    output      [WORD_SIZE * NOF_PES -1:0]  out

    );

    reg [NOF_LEVELS-1:0]            counter;
    wire [2 * WORD_SIZE * NOF_PES -1:0]  temp;


    //generate counter
    always @(posedge clk) begin
        counter <= rst ? 0 : counter + 1;
    end

    assign temp = {in,in};
    assign out = temp[counter * WORD_SIZE +: NOF_PES * WORD_SIZE];

endmodule

barrel_shifter/verification/tb.v
`timescale 1ns/1ps
module tb;
integer    cycles;   initial cycles=0;
integer    errors;   initial errors=0;
integer    wrongs;   initial wrongs=0;
integer    panics;   initial panics=0;
integer    corrects; initial corrects=0;
reg [31:0] marker;   initial marker=0;
reg [31:0] marker0;   initial marker0=0;
reg [31:0] marker1;   initial marker1=0;
reg [31:0] marker2;   initial marker2=0;
reg [31:0] marker3;   initial marker3=0;
reg [31:0] Index;   initial Index=0;
reg [31:0] ID;   initial ID=0;
parameter WORD_SIZE = 256;
parameter NOF_PES = 16;
parameter NOF_LEVELS = $clog2(NOF_PES);
parameter GROUP_SIZE_WIDTH = (NOF_LEVELS + 1);
reg  clk;
reg [((WORD_SIZE * NOF_PES) - 1):0] in;
wire [((WORD_SIZE * NOF_PES) - 1):0] out;
reg  rst;
reg rst_n;

always begin
    clk=0;
    #10;
    clk=1;
    #3;
    $python("negedge()");
    #7;
end
initial begin
    $dumpvars(0,tb);
    rst_n = 0;
    clk = 0;
    in = 0;
    rst = 1;
    #100;
    rst=0;
end
barrel_shifter dut (
     .clk(clk)
    ,.in(in[((WORD_SIZE * NOF_PES) - 1):0])
    ,.out(out[((WORD_SIZE * NOF_PES) - 1):0])
    ,.rst(rst)
);

reg [1023:0] testname;
initial begin
    if ($value$plusargs("LOG=%s",testname)) begin 
        $python("pymonname()",testname);
    end 


    if ($value$plusargs("SEQ=%s",testname)) begin 
         $display(" Running SEQ= %s.",testname); 
    end else begin
        testname = 0;
        $display(" default test");
    end 
    #10;
    if (testname!=0) $python("sequence()",testname);
end 
endmodule


module inout_driver ( inout io , input dflt );

reg val; initial val=0;
reg drive; initial drive=0;
assign io = drive ? val : 1'bz;
assign (pull1,pull0) io = dflt;

endmodule

barrel_shifter/verification/work/dump.vcd
$date
	Wed Mar 22 15:35:49 2023
$end
$version
	Icarus Verilog
$end
$timescale
	1ps
$end
$scope module tb $end
$var wire 128 ! out [127:0] $end
$var reg 32 " ID [31:0] $end
$var reg 32 # Index [31:0] $end
$var reg 1 $ clk $end
$var reg 128 % in [127:0] $end
$var reg 32 & marker [31:0] $end
$var reg 32 ' marker0 [31:0] $end
$var reg 32 ( marker1 [31:0] $end
$var reg 32 ) marker2 [31:0] $end
$var reg 32 * marker3 [31:0] $end
$var reg 1 + rst $end
$var reg 1 , rst_n $end
$var reg 1024 - testname [1023:0] $end
$var integer 32 . corrects [31:0] $end
$var integer 32 / cycles [31:0] $end
$var integer 32 0 errors [31:0] $end
$var integer 32 1 panics [31:0] $end
$var integer 32 2 wrongs [31:0] $end
$scope module dut $end
$var wire 1 $ clk $end
$var wire 128 3 in [127:0] $end
$var wire 1 + rst $end
$var wire 256 4 temp [255:0] $end
$var wire 128 5 out [127:0] $end
$var reg 4 6 counter [3:0] $end
$upscope $end
$upscope $end
$enddefinitions $end
#0
$dumpvars
bx 6
bx 5
b0 4
b0 3
b0 2
b0 1
b0 0
b0 /
b0 .
b0 -
0,
1+
b0 *
b0 )
b0 (
b0 '
b0 &
b0 %
0$
b0 #
b0 "
bx !
$end
#10000
b0 !
b0 5
b0 6
1$
#20000
0$
#30000
1$
#40000
0$
#50000
1$
#60000
0$
#70000
1$
#80000
0$
#90000
1$
#100000
0$
0+
#110000
b1 6
1$
#120000
0$
#130000
b10 6
1$
#133000
b1 /
#140000
0$
#150000
b11 6
1$
#153000
b1101000011100000111100000000000000010000001000000011000001000000010100000110000001110000100000001001000010100000101100001100 !
b1101000011100000111100000000000000010000001000000011000001000000010100000110000001110000100000001001000010100000101100001100 5
b1000000100000001100000100000001010000011000000111000010000000100100001010000010110000110000001101000011100000111100000000000000010000001000000011000001000000010100000110000001110000100000001001000010100000101100001100000011010000111000001111 4
b10000001000000011000001000000010100000110000001110000100000001001000010100000101100001100000011010000111000001111 %
b10000001000000011000001000000010100000110000001110000100000001001000010100000101100001100000011010000111000001111 3
b10 /
#160000
0$
#170000
b1100000011010000111000001111000000000000000100000010000000110000010000000101000001100000011100001000000010010000101000001011 !
b1100000011010000111000001111000000000000000100000010000000110000010000000101000001100000011100001000000010010000101000001011 5
b100 6
1$
#173000
b11 /
#180000
0$
#190000
b1011000011000000110100001110000011110000000000000001000000100000001100000100000001010000011000000111000010000000100100001010 !
b1011000011000000110100001110000011110000000000000001000000100000001100000100000001010000011000000111000010000000100100001010 5
b101 6
1$
#193000
b100 /
#200000
0$
#210000
b1010000010110000110000001101000011100000111100000000000000010000001000000011000001000000010100000110000001110000100000001001 !
b1010000010110000110000001101000011100000111100000000000000010000001000000011000001000000010100000110000001110000100000001001 5
b110 6
1$
#213000
b101 /
#220000
0$
#230000
b1001000010100000101100001100000011010000111000001111000000000000000100000010000000110000010000000101000001100000011100001000 !
b1001000010100000101100001100000011010000111000001111000000000000000100000010000000110000010000000101000001100000011100001000 5
b111 6
1$
#233000
b110 /
#240000
0$
#250000
b1000000010010000101000001011000011000000110100001110000011110000000000000001000000100000001100000100000001010000011000000111 !
b1000000010010000101000001011000011000000110100001110000011110000000000000001000000100000001100000100000001010000011000000111 5
b1000 6
1$
#253000
b111 /
#260000
0$
#270000
b111000010000000100100001010000010110000110000001101000011100000111100000000000000010000001000000011000001000000010100000110 !
b111000010000000100100001010000010110000110000001101000011100000111100000000000000010000001000000011000001000000010100000110 5
b1001 6
1$
#273000
b1000 /
#280000
0$
#290000
b110000001110000100000001001000010100000101100001100000011010000111000001111000000000000000100000010000000110000010000000101 !
b110000001110000100000001001000010100000101100001100000011010000111000001111000000000000000100000010000000110000010000000101 5
b1010 6
1$
#293000
b1001 /
#300000
0$
#310000
b101000001100000011100001000000010010000101000001011000011000000110100001110000011110000000000000001000000100000001100000100 !
b101000001100000011100001000000010010000101000001011000011000000110100001110000011110000000000000001000000100000001100000100 5
b1011 6
1$
#313000
b1010 /
#320000
0$
#330000
b100000001010000011000000111000010000000100100001010000010110000110000001101000011100000111100000000000000010000001000000011 !
b100000001010000011000000111000010000000100100001010000010110000110000001101000011100000111100000000000000010000001000000011 5
b1100 6
1$
#333000
b1011 /
#340000
0$
#350000
b11000001000000010100000110000001110000100000001001000010100000101100001100000011010000111000001111000000000000000100000010 !
b11000001000000010100000110000001110000100000001001000010100000101100001100000011010000111000001111000000000000000100000010 5
b1101 6
1$
#353000
b1100 /
#360000
0$
#370000
b10000000110000010000000101000001100000011100001000000010010000101000001011000011000000110100001110000011110000000000000001 !
b10000000110000010000000101000001100000011100001000000010010000101000001011000011000000110100001110000011110000000000000001 5
b1110 6
1$
#373000
b1101 /
#380000
0$
#390000
b1000000100000001100000100000001010000011000000111000010000000100100001010000010110000110000001101000011100000111100000000 !
b1000000100000001100000100000001010000011000000111000010000000100100001010000010110000110000001101000011100000111100000000 5
b1111 6
1$
#393000
b1110 /
#400000
0$
#410000
b10000001000000011000001000000010100000110000001110000100000001001000010100000101100001100000011010000111000001111 !
b10000001000000011000001000000010100000110000001110000100000001001000010100000101100001100000011010000111000001111 5
b0 6
1$
#413000
b1111 /
#420000
0$
#430000
b1111000000000000000100000010000000110000010000000101000001100000011100001000000010010000101000001011000011000000110100001110 !
b1111000000000000000100000010000000110000010000000101000001100000011100001000000010010000101000001011000011000000110100001110 5
b1 6
1$
#433000
b10000 /
#440000
0$
#450000
b1110000011110000000000000001000000100000001100000100000001010000011000000111000010000000100100001010000010110000110000001101 !
b1110000011110000000000000001000000100000001100000100000001010000011000000111000010000000100100001010000010110000110000001101 5
b10 6
1$
#453000
b10001 /
#460000
0$
#470000
b1101000011100000111100000000000000010000001000000011000001000000010100000110000001110000100000001001000010100000101100001100 !
b1101000011100000111100000000000000010000001000000011000001000000010100000110000001110000100000001001000010100000101100001100 5
b11 6
1$
#473000
b10010 /
#480000
0$
#490000
b1100000011010000111000001111000000000000000100000010000000110000010000000101000001100000011100001000000010010000101000001011 !
b1100000011010000111000001111000000000000000100000010000000110000010000000101000001100000011100001000000010010000101000001011 5
b100 6
1$
#493000
b10011 /
#500000
0$
#510000
b1011000011000000110100001110000011110000000000000001000000100000001100000100000001010000011000000111000010000000100100001010 !
b1011000011000000110100001110000011110000000000000001000000100000001100000100000001010000011000000111000010000000100100001010 5
b101 6
1$
#513000
b10100 /
#520000
0$
#530000
b1010000010110000110000001101000011100000111100000000000000010000001000000011000001000000010100000110000001110000100000001001 !
b1010000010110000110000001101000011100000111100000000000000010000001000000011000001000000010100000110000001110000100000001001 5
b110 6
1$
#533000
b10101 /
